LICENSE
README.md
setup.py
nusterTool/__init__.py
nusterTool/test.py
nusterTool.egg-info/PKG-INFO
nusterTool.egg-info/SOURCES.txt
nusterTool.egg-info/dependency_links.txt
nusterTool.egg-info/top_level.txt